
[

	{
		"name":"nike",
		"url":"https://www.nike.com/w/new-shoes-3n82yzy7ok?sort=newest"
	},

	{
		"name":"innvictus",
		"url":"https://www.innvictus.com/lanzamientos"
	},

	{
		"name":"lustmexico",
		"url":"https://www.lustmexico.com/"
	},

	{
		"name":"laces",
		"url":"https://laces.mx/"
	},

	{
		"name":"99store",
		"url":"https://99store.mx/collections/calzado"
	},

	{
		"name":"alivemexico",
		"url":"https://www.alivemexico.com/18-web?order=product.position.asc"
	},

	{
		"name":"twofeetundr",
		"url":"https://twofeetundr.com/collections/sneakers?sort_by=created-descending"
	},

	{
		"name":"soul",
		"url":"https://soul.com.mx/nuevo.html?start=0"
	},

	{
		"name":"taf",
		"url":"https://www.taf.com.mx/"
	}

]