[{"title":"Nuevo Producto","categoria":"Sneakers","name":"W AIR MAX 270 REACT","marca":"Nike","departamento":"WOMEN´S","price":"$2,309.30","url":"https://www.taf.com.mx/w-air-max-270-react-cz6685-100/p","img":"https://tafmx.vteximg.com.br/arquivos/ids/205213-398-512/CZ6685-100-1.jpg.png?v=637339174468300000"},{"title":"Nuevo Producto","categoria":"Sneakers","name":"NIKE COURT VINTAGE PREM","marca":"Nike","departamento":"MEN´S","price":"$1,049.30","url":"https://www.taf.com.mx/nike-court-vintage-prem-ct1726-002/p","img":"https://tafmx.vteximg.com.br/arquivos/ids/216723-398-512/CT1726-002-1.png?v=637401979616170000"},{"title":"Nuevo Producto","categoria":"Sneakers","name":"AIR MAX 270 REACT","marca":"Nike","departamento":"MEN´S","price":"$1,979.40","url":"https://www.taf.com.mx/air-max-270-react-ct1280-100/p","img":"https://tafmx.vteximg.com.br/arquivos/ids/216699-398-512/CT1280-100-1.png?v=637401978678170000"},{"title":"Nuevo Producto","categoria":"Sneakers","name":"W AIR MAX 270 REACT SE","marca":"Nike","departamento":"WOMEN´S","price":"$2,344.30","url":"https://www.taf.com.mx/w-air-max-270-react-se-ck6929-400/p","img":"https://tafmx.vteximg.com.br/arquivos/ids/207620-398-512/Portada.png?v=637359508772530000"},{"title":"Nuevo Producto","categoria":"Sneakers","name":"AIR MAX 270 REACT WW","marca":"Nike","departamento":"MEN´S","price":"$2,009.40","url":"https://www.taf.com.mx/air-max-270-react-ww-ck6457-001/p","img":"https://tafmx.vteximg.com.br/arquivos/ids/202515-398-512/ck6457-001-1.png?v=637320705637570000"}]